lark_connect/__init__.py
lark_connect/core.py
lark_connect/doc_manager.py
lark_connect/exceptions.py
lark_connect/sheet_manager.py
lark_connect/typings.py
lark_connect-0.0.5.dist-info/METADATA
lark_connect-0.0.5.dist-info/WHEEL
lark_connect-0.0.5.dist-info/top_level.txt
lark_connect-0.0.5.dist-info/RECORD
