Metadata-Version: 2.4
Name: lark-connect
Version: 0.0.5
Summary: A Python package for integrating with Lark API to send messages, manage bots, and interact with Lark apps.
Author: wontae.jeon
Author-email: wontae@aidenlab.io
Keywords: lark,incode8
Classifier: Programming Language :: Python :: 3.8
Classifier: Programming Language :: Python :: 3.9
Classifier: Programming Language :: Python :: 3.10
Classifier: Programming Language :: Python :: 3.11
Classifier: Programming Language :: Python :: 3.12
Requires-Python: >=3.8
Requires-Dist: requests
Dynamic: author
Dynamic: author-email
Dynamic: classifier
Dynamic: description
Dynamic: description-content-type
Dynamic: keywords
Dynamic: requires-dist
Dynamic: requires-python
Dynamic: summary
